seerpy/__init__.py
seerpy/from seerpy import Seer.py
seerpy/import requests.py
seerpy/payloads.py
seerpy/seer.py
seerpy/setup.py
seerpy-0.1.8.dist-info/licenses/LICENSE
seerpy-0.1.8.dist-info/METADATA
seerpy-0.1.8.dist-info/WHEEL
seerpy-0.1.8.dist-info/top_level.txt
seerpy-0.1.8.dist-info/RECORD
